MANIFEST.in
README.rst
setup.py
hktestpack/__init__.py
hktestpack.egg-info/PKG-INFO
hktestpack.egg-info/SOURCES.txt
hktestpack.egg-info/dependency_links.txt
hktestpack.egg-info/not-zip-safe
hktestpack.egg-info/top_level.txt
hktestpack/hktest/__init__.py
hktestpack/hktest/__version__.py
hktestpack/hktest/hktest.py
hktestpack/hktest/utils.py
hktestpack/hktest1/__init__.py
hktestpack/hktest1/hktest1.py