Metadata-Version: 1.1
Name: hktestpack
Version: 1.0.2
Summary: hktest module to test pypi
Home-page: https://github.com/hekai000/gopl
Author: HeKai
Author-email: hekai@kylinos.com.cn
License: Apache License, Version 2.0
Platform: linux/Windows
Classifier: Development Status :: 3 - Alpha
Classifier: Topic :: Text Processing
Classifier: License :: OSI Approved :: MIT License
Classifier: Programming Language :: Python :: 2
Classifier: Programming Language :: Python :: 2.7
Classifier: Programming Language :: Python :: 3
Classifier: Programming Language :: Python :: 3.5
